ibackupy/__init__.py
ibackupy/backup.py
ibackupy-0.1.2.dist-info/LICENSE
ibackupy-0.1.2.dist-info/METADATA
ibackupy-0.1.2.dist-info/WHEEL
ibackupy-0.1.2.dist-info/RECORD
