Metadata-Version: 2.1
Name: ibackupy
Version: 0.1.2
Summary: A Python package to parse iTunes backups
Home-page: https://github.com/xleven/ibackupy
License: MIT
Author: xleven
Author-email: xleven@outlook.com
Requires-Python: >=3.8,<4.0
Classifier: License :: OSI Approved :: MIT License
Classifier: Programming Language :: Python :: 3
Classifier: Programming Language :: Python :: 3.8
Classifier: Programming Language :: Python :: 3.9
Classifier: Programming Language :: Python :: 3.10
Classifier: Programming Language :: Python :: 3.11
